<?xml version="1.0" encoding="utf-8" ?>
<movie width="220" height="28" framerate="30">
	<background color="#ffffff"/>
	<frame>
		<clip import="BooBuilds_classes.swf" />
		<library>
			<clip id="appBuilds" class="com.boobuilds.Controller" />
			<clip id="BooBuildsIcon" import="BuildsIconTransparent.png"/>
			<clip id="BooBuildsNoSign" import="NoSign.png"/>
			<clip id="BooBuildsWarning" import="warning_sign_bold.png"/>
			<clip id="BooBuildsTank" import="Tank.png"/>
			<clip id="BooBuildsDPS" import="DPS.png"/>
			<clip id="BooBuildsHeals" import="Heals.png"/>
			<clip id="BooBuildsTank2" import="Tank2.png"/>
			<clip id="BooBuildsDPS2" import="DPS2.png"/>
			<clip id="BooBuildsHeals2" import="Heals2.png"/>
			<clip id="BooBuildsHelp" import="questionButton.png"/>
			<clip id="BooBuildsBlood" import="Blood.png"/>
			<clip id="BooBuildsChaos" import="Chaos.png"/>
			<clip id="BooBuildsEle" import="Elementalism.png"/>
			<clip id="BooBuildsFist" import="Fist.png"/>
			<clip id="BooBuildsHammer" import="Hammer.png"/>
			<clip id="BooBuildsPistol" import="Pistol.png"/>
			<clip id="BooBuildsRifle" import="Rifle.png"/>
			<clip id="BooBuildsShotgun" import="Shotgun.png"/>
			<clip id="BooBuildsSword" import="Sword.png"/>
			<clip id="BooBuildsOne" import="One.png"/>
			<clip id="BooBuildsTwo" import="Two.png"/>
			<clip id="BooBuildsThree" import="Three.png"/>
			<clip id="BooBuildsFour" import="Four.png"/>
			<clip id="BooBuildsFive" import="Five.png"/>
			<clip id="BooBuildsSix" import="Six.png"/>
			<clip id="BooBuildsSeven" import="Seven.png"/>
			<clip id="BooBuildsEight" import="Eight.png"/>
			<clip id="BooBuildsNine" import="Nine.png"/>
			<clip id="BooBuildsTen" import="Ten.png"/>
			<clip id="BooBuildsEleven" import="Eleven.png"/>
			<clip id="BooBuildsTwelve" import="Twelve.png"/>
			<font id="tahoma" import="fonts/tahoma.ttf" name="Tahoma "/>
		</library>
		<place id="appBuilds" name="appBuilds" depth="100" />
		<place id="BooBuildsIcon" name="BooBuildsIcon" depth="101" />
	</frame>
</movie>
